robocopy/__init__.py
robocopy/robocopy.py
py_robocopy-0.0.5.dist-info/LICENSE
py_robocopy-0.0.5.dist-info/METADATA
py_robocopy-0.0.5.dist-info/WHEEL
py_robocopy-0.0.5.dist-info/top_level.txt
py_robocopy-0.0.5.dist-info/RECORD
