Metadata-Version: 2.1
Name: py-robocopy
Version: 0.0.5
Summary: Copies file data from one location to another.
Author-email: Suyash Sonkesaria <suyashsonkesaria@gmail.com>
Project-URL: Homepage, https://github.com/suyashsonkesaria/robocopy
Project-URL: Bug Tracker, https://github.com/suyashsonkesaria/robocopy/issues
Classifier: Programming Language :: Python :: 3
Classifier: License :: OSI Approved :: MIT License
Classifier: Operating System :: OS Independent
Requires-Python: >=3.7
License-File: LICENSE
